[{"ticker": "XOM", "cusip": "30231G102", "name": "Exxon Mobil Corp", "pct_val": 22.98815526136}, {"ticker": "CVX", "cusip": "166764100", "name": "Chevron Corp", "pct_val": 19.72875000236}, {"ticker": "COP", "cusip": "20825C104", "name": "ConocoPhillips", "pct_val": 4.543549117991}, {"ticker": "EOG", "cusip": "26875P101", "name": "EOG Resources Inc", "pct_val": 4.502407489333}, {"ticker": "PXDEUR", "cusip": "723787107", "name": "Pioneer Natural Resources Co", "pct_val": 4.483938900429}, {"ticker": "SLB", "cusip": "806857108", "name": "Schlumberger NV", "pct_val": 4.405664431161}, {"ticker": "MPC", "cusip": "56585A102", "name": "Marathon Petroleum Corp", "pct_val": 4.297332387744}, {"ticker": "OXY", "cusip": "674599105", "name": "Occidental Petroleum Corp", "pct_val": 3.973184543203}, {"ticker": "VLO", "cusip": "91913Y100", "name": "Valero Energy Corp", "pct_val": 3.652411773227}, {"ticker": "DVN", "cusip": "25179M103", "name": "Devon Energy Corp", "pct_val": 3.416257697193}, {"ticker": "PSX", "cusip": "718546104", "name": "Phillips 66", "pct_val": 3.369140811887}, {"ticker": "WMB", "cusip": "969457100", "name": "Williams Cos Inc/The", "pct_val": 3.026947080261}, {"ticker": "KMI", "cusip": "49456B101", "name": "Kinder Morgan Inc", "pct_val": 2.862496629447}, {"ticker": "HES", "cusip": "42809H107", "name": "Hess Corp", "pct_val": 2.635114632239}, {"ticker": "OKE", "cusip": "682680103", "name": "ONEOK Inc", "pct_val": 1.98668604555}, {"ticker": "HAL", "cusip": "406216101", "name": "Halliburton Co", "pct_val": 1.937391627741}, {"ticker": "FANG", "cusip": "25278X109", "name": "Diamondback Energy Inc", "pct_val": 1.857827638811}, {"ticker": "BKR", "cusip": "05722G100", "name": "Baker Hughes Co", "pct_val": 1.839980656666}, {"ticker": "CTRA", "cusip": "127097103", "name": "Coterra Energy Inc", "pct_val": 1.803078348577}, {"ticker": "MRO*", "cusip": "565849106", "name": "Marathon Oil Corp", "pct_val": 1.3274975969}, {"ticker": "APA", "cusip": "03743Q108", "name": "APA Corp", "pct_val": 0.968653307513}]