[{"ticker": "XOM", "cusip": "30231G102", "name": "Exxon Mobil Corp", "pct_val": 23.32721019534}, {"ticker": "CVX", "cusip": "166764100", "name": "Chevron Corp", "pct_val": 16.04951730955}, {"ticker": "COP", "cusip": "20825C104", "name": "ConocoPhillips", "pct_val": 7.691586310703}, {"ticker": "WMB", "cusip": "969457100", "name": "Williams Cos Inc/The", "pct_val": 4.445313768685}, {"ticker": "EOG", "cusip": "26875P101", "name": "EOG Resources Inc", "pct_val": 4.321725125043}, {"ticker": "OKE", "cusip": "682680103", "name": "ONEOK Inc", "pct_val": 4.067155700209}, {"ticker": "SLB", "cusip": "806857108", "name": "Schlumberger NV", "pct_val": 3.868696826014}, {"ticker": "KMI", "cusip": "49456B101", "name": "Kinder Morgan Inc", "pct_val": 3.643793238499}, {"ticker": "PSX", "cusip": "718546104", "name": "Phillips 66", "pct_val": 3.369222931}, {"ticker": "MPC", "cusip": "56585A102", "name": "Marathon Petroleum Corp", "pct_val": 3.041712936991}, {"ticker": "HES", "cusip": "42809H107", "name": "Hess Corp", "pct_val": 2.916758595041}, {"ticker": "TRGP", "cusip": "87612G101", "name": "Targa Resources Corp", "pct_val": 2.88818804733}, {"ticker": "BKR", "cusip": "05722G100", "name": "Baker Hughes Co", "pct_val": 2.875014339361}, {"ticker": "VLO", "cusip": "91913Y100", "name": "Valero Energy Corp", "pct_val": 2.762413742136}, {"ticker": "OXY", "cusip": "674599105", "name": "Occidental Petroleum Corp", "pct_val": 2.203259307099}, {"ticker": "EQT", "cusip": "26884L109", "name": "EQT Corp", "pct_val": 2.106320826096}, {"ticker": "FANG", "cusip": "25278X109", "name": "Diamondback Energy Inc", "pct_val": 1.97395624579}, {"ticker": "TPL", "cusip": "88262P102", "name": "Texas Pacific Land Corp", "pct_val": 1.649073757815}, {"ticker": "DVN", "cusip": "25179M103", "name": "Devon Energy Corp", "pct_val": 1.623180425317}, {"ticker": "EXE", "cusip": "165167735", "name": "Expand Energy Corp", "pct_val": 1.546682146222}, {"ticker": "HAL", "cusip": "406216101", "name": "Halliburton Co", "pct_val": 1.455065741795}, {"ticker": "CTRA", "cusip": "127097103", "name": "Coterra Energy Inc", "pct_val": 1.406163778509}, {"ticker": "APA", "cusip": "03743Q108", "name": "APA Corp", "pct_val": 0.51376412176}]